beerest/__init__.py
beerest/core/__init__.py
beerest/core/assertions.py
beerest/core/expect.py
beerest/core/request.py
beerest/core/response.py
beerest/core/schema.py
beerest/core/test.py
beerest/tests/__init__.py
beerest/tests/test_assertions.py
beerest/tests/test_expect.py
beerest/tests/test_request.py
beerest/tests/test_response.py
beerest/tests/test_schema.py
example/__init__.py
example/test_example.py
beerest-0.2.0.dist-info/LICENCE
beerest-0.2.0.dist-info/METADATA
beerest-0.2.0.dist-info/WHEEL
beerest-0.2.0.dist-info/top_level.txt
beerest-0.2.0.dist-info/RECORD
