Metadata-Version: 2.1
Name: beerest
Version: 0.2.0
Summary: A beerest é uma lib de testes de API que combina simplicidade, robustez e elegância, oferecendo uma experiência fluente de escrita de testes.
Home-page: https://github.com/eliezer-castro/beerest
Author: eliezer-gino
Author-email: eliezergino@gmail.com
Classifier: Programming Language :: Python :: 3
Classifier: License :: OSI Approved :: MIT License
Classifier: Operating System :: OS Independent
Requires-Python: >=3.12.1
License-File: LICENCE
Requires-Dist: httpx
Requires-Dist: jsonpath-ng
Requires-Dist: dataclasses; python_version < "3.7"
